py_cr/pycrlib.cpython-312-darwin.so
py_chains_of_recurrences-0.1b11.dist-info/RECORD
py_chains_of_recurrences-0.1b11.dist-info/WHEEL
py_chains_of_recurrences-0.1b11.dist-info/METADATA
py_chains_of_recurrences-0.1b11.dist-info/licenses/LICENSE
