Metadata-Version: 2.2
Name: py_chains_of_recurrences
Version: 0.1b11
Summary: A chains of recurrences library for python
Requires-Python: >=3.10
